pycogaps.cpython-38-darwin.so
pycogaps-0.0.1.dist-info/LICENSE
pycogaps-0.0.1.dist-info/METADATA
pycogaps-0.0.1.dist-info/WHEEL
pycogaps-0.0.1.dist-info/top_level.txt
pycogaps-0.0.1.dist-info/RECORD
