Metadata-Version: 2.1
Name: pycogaps
Version: 0.0.1
Summary: PyCoGAPS
Home-page: https://github.com/FertigLab/pycogaps
Author: Jeanette Johnson
Author-email: jjohn450@jhmi.edu
License: MIT
License-File: LICENSE
Requires-Dist: pybind11 (>=2.2)
